third semester/BBM233/ASS2/half_adder.v
`timescale 1ns/10ps

module half_adder(
    input A, B,
    output S, C
);

	// Your code goes here.  DO NOT change anything that is already given! Otherwise, you will not be able to pass the tests!
    assign S = A ^ B;
    assign C = A & B;  

endmodule

third semester/BBM233/assignment1/full_adder.v
`timescale 1ns/10ps
module full_adder(
    input A, B, Cin,
    output S, Cout
);

	// Your code goes here.  DO NOT change anything that is already given! Otherwise, you will not be able to pass the tests!
    wire S0, Cout0, Cout1;
    half_adder tmp0(.A(A), .B(B), .S(S0), .C(Cout0));
    half_adder tmp1(.A(S0), .B(Cin), .S(S), .C(Cout1));
    or or0(Cout, Cout0, Cout1);

endmodule

third semester/BBM233/assignment1/full_adder_tb.v
`timescale 1ns/10ps

module full_adder_tb;
    // Your code goes here.  DO NOT change anything that is already given! Otherwise, you will not be able to pass the tests!
    reg A, B, Cin;
    wire S, Cout;
    full_adder tmp(.A(A), .B(B), .Cin(Cin), .S(S), .Cout(Cout));
    initial begin
        A = 1'b0; B= 1'b0; Cin = 1'b0;
        #10 A = 1'b0; B= 1'b0; Cin = 1'b1;
        #10 A = 1'b0; B= 1'b1; Cin = 1'b0;
        #10 A = 1'b0; B= 1'b1; Cin = 1'b1;
        #10 A = 1'b1; B= 1'b0; Cin = 1'b0;
        #10 A = 1'b1; B= 1'b0; Cin = 1'b1;
        #10 A = 1'b1; B= 1'b1; Cin = 1'b0;
        #10 A = 1'b1; B= 1'b1; Cin = 1'b1;
        #10 $finish;
    end
endmodule

third semester/BBM233/ASS2/full_adder_tb.vcd
$date
	Mon Dec 04 23:03:54 2023
$end
$version
	Icarus Verilog
$end
$timescale
	10ps
$end
$scope module full_adder_tb $end
$var wire 1 ! S $end
$var wire 1 " Cout $end
$var reg 1 # A $end
$var reg 1 $ B $end
$var reg 1 % Cin $end
$upscope $end
$enddefinitions $end
#0
$dumpvars
0%
0$
0#
0"
0!
$end
#1000
1!
1%
#2000
0%
1$
#3000
1"
0!
1%
#4000
0"
1!
0%
0$
1#
#5000
1"
0!
1%
#6000
0%
1$
#7000
1!
1%
