third semester/BBM233/ASS2/half_adder.v
`timescale 1ns/10ps

module half_adder(
    input A, B,
    output S, C
);

	// Your code goes here.  DO NOT change anything that is already given! Otherwise, you will not be able to pass the tests!
    assign S = A ^ B;
    assign C = A & B;  

endmodule

third semester/BBM233/assignment1/full_adder.v
`timescale 1ns/10ps
module full_adder(
    input A, B, Cin,
    output S, Cout
);

	// Your code goes here.  DO NOT change anything that is already given! Otherwise, you will not be able to pass the tests!
    wire S0, Cout0, Cout1;
    half_adder tmp0(.A(A), .B(B), .S(S0), .C(Cout0));
    half_adder tmp1(.A(S0), .B(Cin), .S(S), .C(Cout1));
    or or0(Cout, Cout0, Cout1);

endmodule

third semester/BBM233/ASS2/multiplier.v
`timescale 1ns/10ps

module multiplier (
    input [2:0] A, B,
    output [5:0] P
);
    and and0_inst(P[0], A[0], B[0]);
    wire and1, and2, and3, and4, and5, and6, and7, and8;
    //change all to structural design
    and and1_inst(and1, A[1], B[0]);
    
    and and2_inst(and2, A[0], B[1]);
    wire c0;
    half_adder ha1(.A(and2), .B(and1), .S(P[1]), .C(c0));

    and and3_inst(and3, A[2], B[0]);
    and and4_inst(and4, A[1], B[1]);
    wire s1,c1;
    half_adder ha2(.A(and4), .B(and3), .S(s1), .C(c1));
    wire c2;
    and and5_inst(and5, A[0], B[2]);
    full_adder fa1(.A(and5), .B(s1), .Cin(c0), .S( P[2]    ), .Cout(c2));
    and and6_inst(and6, A[2], B[1]);
    and and7_inst(and7, A[1], B[2]);
    wire s3,c3;
    full_adder fa2(.A(and7), .B(and6), .Cin(c1), .S(s3    ), .Cout(c3));
    wire c4;
    half_adder ha3(.A(s3), .B(c2), .S(P[3]), .C(c4));
    and and8_inst(and8, A[2], B[2]);
    full_adder fa3(.A(and8), .B(c3), .Cin(c4), .S(P[4]), .Cout(P[5]));
	// Your code goes here.  DO NOT change anything that is already given! Otherwise, you will not be able to pass the tests!


endmodule

third semester/BBM233/assignment1/multiplier_tb.v
`timescale 1ns/10ps

module multiplier_tb;

	// Your code goes here.  DO NOT change anything that is already given! Otherwise, you will not be able to pass the tests!
	reg [2:0] A, B;
	wire [5:0] P;
	multiplier multiplier_inst(.A(A), .B(B), .P(P));
	integer i, j;

	initial begin
		for (i = 0; i < 8; i = i + 1) begin
			for (j = 0; j < 8; j = j + 1) begin
				A = i;
				B = j;
				#10;
			end
		end
		$finish;
	end
endmodule

third semester/BBM233/ASS2/multiplier_tb.vcd
$date
	Mon Dec 04 23:41:03 2023
$end
$version
	Icarus Verilog
$end
$timescale
	10ps
$end
$scope module multiplier_tb $end
$var wire 6 ! P [5:0] $end
$var reg 3 " A [2:0] $end
$var reg 3 # B [2:0] $end
$var integer 32 $ i [31:0] $end
$var integer 32 % j [31:0] $end
$upscope $end
$enddefinitions $end
#0
$dumpvars
b0 %
b0 $
b0 #
b0 "
b0 !
$end
#1000
b1 #
b1 %
#2000
b10 #
b10 %
#3000
b11 #
b11 %
#4000
b100 #
b100 %
#5000
b101 #
b101 %
#6000
b110 #
b110 %
#7000
b111 #
b111 %
#8000
b0 #
b1 "
b1 $
b0 %
#9000
b1 !
b1 #
b1 %
#10000
b10 !
b10 #
b10 %
#11000
b11 !
b11 #
b11 %
#12000
b100 !
b100 #
b100 %
#13000
b101 !
b101 #
b101 %
#14000
b110 !
b110 #
b110 %
#15000
b111 !
b111 #
b111 %
#16000
b0 !
b0 #
b10 "
b10 $
b0 %
#17000
b10 !
b1 #
b1 %
#18000
b100 !
b10 #
b10 %
#19000
b110 !
b11 #
b11 %
#20000
b1000 !
b100 #
b100 %
#21000
b1010 !
b101 #
b101 %
#22000
b1100 !
b110 #
b110 %
#23000
b1110 !
b111 #
b111 %
#24000
b0 !
b0 #
b11 "
b11 $
b0 %
#25000
b11 !
b1 #
b1 %
#26000
b110 !
b10 #
b10 %
#27000
b1001 !
b11 #
b11 %
#28000
b1100 !
b100 #
b100 %
#29000
b1111 !
b101 #
b101 %
#30000
b10010 !
b110 #
b110 %
#31000
b10101 !
b111 #
b111 %
#32000
b0 !
b0 #
b100 "
b100 $
b0 %
#33000
b100 !
b1 #
b1 %
#34000
b1000 !
b10 #
b10 %
#35000
b1100 !
b11 #
b11 %
#36000
b10000 !
b100 #
b100 %
#37000
b10100 !
b101 #
b101 %
#38000
b11000 !
b110 #
b110 %
#39000
b11100 !
b111 #
b111 %
#40000
b0 !
b0 #
b101 "
b101 $
b0 %
#41000
b101 !
b1 #
b1 %
#42000
b1010 !
b10 #
b10 %
#43000
b1111 !
b11 #
b11 %
#44000
b10100 !
b100 #
b100 %
#45000
b11001 !
b101 #
b101 %
#46000
b11110 !
b110 #
b110 %
#47000
b100011 !
b111 #
b111 %
#48000
b0 !
b0 #
b110 "
b110 $
b0 %
#49000
b110 !
b1 #
b1 %
#50000
b1100 !
b10 #
b10 %
#51000
b10010 !
b11 #
b11 %
#52000
b11000 !
b100 #
b100 %
#53000
b11110 !
b101 #
b101 %
#54000
b100100 !
b110 #
b110 %
#55000
b101010 !
b111 #
b111 %
#56000
b0 !
b0 #
b111 "
b111 $
b0 %
#57000
b111 !
b1 #
b1 %
#58000
b1110 !
b10 #
b10 %
#59000
b10101 !
b11 #
b11 %
#60000
b11100 !
b100 #
b100 %
#61000
b100011 !
b101 #
b101 %
#62000
b101010 !
b110 #
b110 %
#63000
b110001 !
b111 #
b111 %
#64000
b1000 $
b1000 %
